setup.py
jrstools/__init__.py
jrstools/error.py
jrstools/export.py
jrstools/make.py
jrstools/node.py
jrstools/schema.py
jrstools.egg-info/PKG-INFO
jrstools.egg-info/SOURCES.txt
jrstools.egg-info/dependency_links.txt
jrstools.egg-info/requires.txt
jrstools.egg-info/top_level.txt
jrstools/templates/docs_index.j2
jrstools/templates/docs_schema.j2
jrstools/templates/docs_subschema.j2
jrstools/templates/export_js.j2
jrstools/templates/export_json.j2