Metadata-Version: 1.0
Name: jrstools
Version: 0.0.1
Summary: json: [rpc, schema] tools
Home-page: http://pythonhosted.org/jrs#jrstools
Author: Stepan Perlov
Author-email: stepanperlov@gmail.com
License: MIT
Platform: linux
